[{"iconID":23,"color_":"#AE01FF","categoryInputValue":"Hobby","userEmail":""},{"iconID":21,"color_":"#000000","categoryInputValue":"fdsf","userEmail":""},{"iconID":7,"color_":"#000000","categoryInputValue":"fdsfs","userEmail":""},{"iconID":13,"color_":"#000000","categoryInputValue":"ghfgh","userEmail":""},{"iconID":7,"color_":"#000000","categoryInputValue":"fdsf","userEmail":""},{"iconID":14,"color_":"#000000","categoryInputValue":"gfdgfd","userEmail":""},{"iconID":14,"color_":"#000000","categoryInputValue":"number1","userEmail":""},{"iconID":7,"color_":"#000000","categoryInputValue":"ghfh","userEmail":""},{"iconID":0,"color_":"#000000","categoryInputValue":"number2","userEmail":""},{"iconID":21,"color_":"#FF7B01","categoryInputValue":"gh","userEmail":""},{"iconID":14,"color_":"#000000","categoryInputValue":"12344123421","userEmail":""},{"iconID":14,"color_":"#000000","categoryInputValue":"dfsg","userEmail":""},{"iconID":7,"color_":"#000000","categoryInputValue":"rtyuturyeytutu","userEmail":""}]